qprogress/__init__.py
qprogress/formatters.py
qprogress/progress_bar.py
qprogress-1.0.2.dist-info/METADATA
qprogress-1.0.2.dist-info/WHEEL
qprogress-1.0.2.dist-info/RECORD
