Metadata-Version: 2.1
Name: qprogress
Version: 1.0.2
Summary: Quera Progress Bar - A decoupled progress bar to show the progress of your loops!
Author: Mohammad Jafari
Author-email: m.jafari9877@gmail.com
Requires-Python: >=3.8,<4.0
Classifier: Programming Language :: Python :: 3
Classifier: Programming Language :: Python :: 3.8
Classifier: Programming Language :: Python :: 3.9
Classifier: Programming Language :: Python :: 3.10
Classifier: Programming Language :: Python :: 3.11
